[
    { 
      "id" : "1",
      "category": "Health",
      "title": "Digital Blood Pressure Monitor",
      "picture": "https://i.ibb.co/x8xhbCD/digital-bload.jpg",
      "categoryColors": {
        "health": "#0052FF",
        "education": "#FF444A",
        "clothing": "#79C23F",
        "food": "#F87147"
      },
      "cardBgColor": {
        "healthCard": "#0052FF26",
        "educationCard": "#FF444A26",
        "clothingCard": "#79C23F26",
        "foodCard": "#F8714726"
      },
      "textButtonBgColor": {
        "healthTxt": "#0052FF26",
        "educationTxt": "#FF444A26",
        "clothingTxt": "#79C23F26",
        "foodTxt": "#F8714726"
      },
      "description": "Track your blood pressure with this easy-to-use digital monitor. Stay healthy and monitor your heart health regularly.",
      "price": 29.99
    },
    {
      "id" : "2",
      "category": "Health",
      "title": "Fitness Tracker Watch",
      "picture": "https://i.ibb.co/DbYTPKF/watch.jpg",
      "categoryColors": {
        "health": "#0052FF",
        "education": "#FF444A",
        "clothing": "#79C23F",
        "food": "#F87147"
      },
      "cardBgColor": {
        "healthCard": "#0052FF26",
        "educationCard": "#FF444A26",
        "clothingCard": "#79C23F26",
        "foodCard": "#F8714726"
      },
      "textButtonBgColor": {
        "healthTxt": "#0052FF26",
        "educationTxt": "#FF444A26",
        "clothingTxt": "#79C23F26",
        "foodTxt": "#F8714726"
      },
      "description": "Stay active and monitor your fitness goals with this sleek fitness tracker watch. It counts steps, measures heart rate, and more.",
      "price": 49.99
    },
    {
      "id" : "3",
      "category": "Education",
      "title": "Educational Building Blocks",
      "picture": "https://i.ibb.co/yXvkPLD/Education.png",
      "categoryColors": {
        "health": "#0052FF",
        "education": "#FF444A",
        "clothing": "#79C23F",
        "food": "#F87147"
      },
      "cardBgColor": {
        "healthCard": "#0052FF26",
        "educationCard": "#FF444A26",
        "clothingCard": "#79C23F26",
        "foodCard": "#F8714726"
      },
      "textButtonBgColor": {
        "healthTxt": "#0052FF26",
        "educationTxt": "#FF444A26",
        "clothingTxt": "#79C23F26",
        "foodTxt": "#F8714726"
      },
      "description": "Enhance your child's learning with these colorful educational building blocks. Perfect for creative play and learning.",
      "price": 19.99
    },
    {
      "id" : "4",
      "category": "Education",
      "title": "Laptop for Online Learning",
      "picture": "https://i.ibb.co/6w592Kh/laptop.jpg",
      "categoryColors": {
        "health": "#0052FF",
        "education": "#FF444A",
        "clothing": "#79C23F",
        "food": "#F87147"
      },
      "cardBgColor": {
        "healthCard": "#0052FF26",
        "educationCard": "#FF444A26",
        "clothingCard": "#79C23F26",
        "foodCard": "#F8714726"
      },
      "textButtonBgColor": {
        "healthTxt": "#0052FF26",
        "educationTxt": "#FF444A26",
        "clothingTxt": "#79C23F26",
        "foodTxt": "#F8714726"
      },
      "description": "Equip your student with the tools they need for online learning. This laptop is perfect for virtual classrooms.",
      "price": 399.99
    },
    {
      "id" : "5",
      "category": "Clothing",
      "title": "Men's Casual T-Shirt",
      "picture": "https://i.ibb.co/Zz41Hh2/Clothing.png",
      "categoryColors": {
        "health": "#0052FF",
        "education": "#FF444A",
        "clothing": "#79C23F",
        "food": "#F87147"
      },
      "cardBgColor": {
        "healthCard": "#0052FF26",
        "educationCard": "#FF444A26",
        "clothingCard": "#79C23F26",
        "foodCard": "#F8714726"
      },
      "textButtonBgColor": {
        "healthTxt": "#0052FF26",
        "educationTxt": "#FF444A26",
        "clothingTxt": "#79C23F26",
        "foodTxt": "#F8714726"
      },
      "description": "Stay comfortable and stylish with this classic men's casual t-shirt. Available in various colors and sizes.",
      "price": 14.99
    },
    {
      "id" : "6",
      "category": "Clothing",
      "title": "Women's Floral Dress",
      "picture": "https://i.ibb.co/cbhKYVs/coloth.jpg",
      "categoryColors": {
        "health": "#0052FF",
        "education": "#FF444A",
        "clothing": "#79C23F",
        "food": "#F87147"
      },
      "cardBgColor": {
        "healthCard": "#0052FF26",
        "educationCard": "#FF444A26",
        "clothingCard": "#79C23F26",
        "foodCard": "#F8714726"
      },
      "textButtonBgColor": {
        "healthTxt": "#0052FF26",
        "educationTxt": "#FF444A26",
        "clothingTxt": "#79C23F26",
        "foodTxt": "#F8714726"
      },
      "description": "Elevate your wardrobe with this beautiful floral dress. Perfect for special occasions and summer days.",
      "price": 39.99
    },
    {
      "id" : "7",
      "category": "Food",
      "title": "Organic Fruit Basket",
      "picture": "https://i.ibb.co/ZxNgLY2/Food.png",
      "categoryColors": {
        "health": "#0052FF",
        "education": "#FF444A",
        "clothing": "#79C23F",
        "food": "#F87147"
      },
      "cardBgColor": {
        "healthCard": "#0052FF26",
        "educationCard": "#FF444A26",
        "clothingCard": "#79C23F26",
        "foodCard": "#F8714726"
      },
      "textButtonBgColor": {
        "healthTxt": "#0052FF26",
        "educationTxt": "#FF444A26",
        "clothingTxt": "#79C23F26",
        "foodTxt": "#F8714726"
      },
      "description": "Enjoy a healthy snack with this organic fruit basket. Filled with a variety of fresh fruits.",
      "price": 29.99
    },
    {
      "id" : "8",
      "category": "Food",
      "title": "missoula food bank",
      "picture": "https://i.ibb.co/2KPV2nR/f.jpg",
      "categoryColors": {
        "health": "#0052FF",
        "education": "#FF444A",
        "clothing": "#79C23F",
        "food": "#F87147"
      },
      "cardBgColor": {
        "healthCard": "#0052FF26",
        "educationCard": "#FF444A26",
        "clothingCard": "#79C23F26",
        "foodCard": "#F8714726"
      },
      "textButtonBgColor": {
        "healthTxt": "#0052FF26",
        "educationTxt": "#FF444A26",
        "clothingTxt": "#79C23F26",
        "foodTxt": "#F8714726"
      },
      "description": "Indulge in luxury with this gourmet chocolate box. Perfect for gifting or self-enjoyment.",
      "price": 19.99
    },
    
    {
      "id" : "9",
        "category": "Food",
        "title": "Helping People",
        "picture": "https://i.ibb.co/sw7hjhk/f2.jpg",
        "categoryColors": {
          "health": "#0052FF",
          "education": "#FF444A",
          "clothing": "#79C23F",
          "food": "#F87147"
        },
        "cardBgColor": {
          "healthCard": "#0052FF26",
          "educationCard": "#FF444A26",
          "clothingCard": "#79C23F26",
          "foodCard": "#F8714726"
        },
        "textButtonBgColor": {
          "healthTxt": "#0052FF26",
          "educationTxt": "#FF444A26",
          "clothingTxt": "#79C23F26",
          "foodTxt": "#F8714726"
        },
        "description": "Experience the rich flavors of our premium coffee beans. Sourced from the finest coffee estates.",
        "price": 12.99
      },
      {
        "id" : "10",
        "category": "Health",
        "title": "Blood Donation",
        "picture": "https://i.ibb.co/TbC4WzW/blood.png",
        "categoryColors": {
          "health": "#0052FF",
          "education": "#FF444A",
          "clothing": "#79C23F",
          "food": "#F87147"
        },
        "cardBgColor": {
          "healthCard": "#0052FF26",
          "educationCard": "#FF444A26",
          "clothingCard": "#79C23F26",
          "foodCard": "#F8714726"
        },
        "textButtonBgColor": {
          "healthTxt": "#0052FF26",
          "educationTxt": "#FF444A26",
          "clothingTxt": "#79C23F26",
          "foodTxt": "#F8714726"
        },
        "description": "Begin your wellness journey with this yoga mat and accessories set. Ideal for yoga and meditation.",
        "price": 34.99
      },
      {
        "id" : "11",
        "category": "Education",
        "title": "Children's Picture Book Set",
        "picture": "https://i.ibb.co/5kbfL24/africa.jpg",
        "categoryColors": {
          "health": "#0052FF",
          "education": "#FF444A",
          "clothing": "#79C23F",
          "food": "#F87147"
        },
        "cardBgColor": {
          "healthCard": "#0052FF26",
          "educationCard": "#FF444A26",
          "clothingCard": "#79C23F26",
          "foodCard": "#F8714726"
        },
        "textButtonBgColor": {
          "healthTxt": "#0052FF26",
          "educationTxt": "#FF444A26",
          "clothingTxt": "#79C23F26",
          "foodTxt": "#F8714726"
        },
        "description": "Inspire young minds with this set of beautifully illustrated children's picture books. Encourage reading and creativity.",
        "price": 22.99
      },
      {
        "id" : "12",
        "category": "Clothing",
        "title": "Give the Gift of Warmth",
        "picture": "https://i.ibb.co/w4fXXnD/warm.jpg",
        "categoryColors": {
          "health": "#0052FF",
          "education": "#FF444A",
          "clothing": "#79C23F",
          "food": "#F87147"
        },
        "cardBgColor": {
          "healthCard": "#0052FF26",
          "educationCard": "#FF444A26",
          "clothingCard": "#79C23F26",
          "foodCard": "#F8714726"
        },
        "textButtonBgColor": {
          "healthTxt": "#0052FF26",
          "educationTxt": "#FF444A26",
          "clothingTxt": "#79C23F26",
          "foodTxt": "#F8714726"
        },
        "description": "Join us in making a difference by participating in our Clothing Donation Drive. Your unused or gently worn clothing items can bring warmth and comfort to those less fortunate.",
        "price": 49.99
      }

  ]
  